jdl.cp39-win_amd64.pyd
jpy-1.3.0.jar
jpy.cp39-win_amd64.pyd
jpyutil.py
jpy-1.3.0.dist-info/LICENSE.txt
jpy-1.3.0.dist-info/METADATA
jpy-1.3.0.dist-info/WHEEL
jpy-1.3.0.dist-info/top_level.txt
jpy-1.3.0.dist-info/RECORD
