Metadata-Version: 2.1
Name: jpy
Version: 1.3.0
Summary: Bi-directional Python-Java bridge
Home-page: https://github.com/jpy-consortium/jpy
Author: Norman Fomferra (Brockmann Consult GmbH) and contributors
Author-email: norman.fomferra@brockmann-consult.de
Maintainer: Brockmann Consult GmbH
Maintainer-email: norman.fomferra@brockmann-consult.de
License: Apache 2.0
Download-URL: https://pypi.python.org/pypi/jpy/1.3.0
Platform: Windows
Platform: Linux
Platform: Darwin
Classifier: Development Status :: 5 - Production/Stable
Classifier: Intended Audience :: Developers
Classifier: License :: OSI Approved :: Apache Software License
Classifier: Programming Language :: Python :: 3.9
Classifier: Programming Language :: Python :: 3.10
Classifier: Programming Language :: Python :: 3.11
Classifier: Programming Language :: Python :: 3.12
Classifier: Programming Language :: Python :: 3.13
Classifier: Programming Language :: Python :: 3.14
Requires-Python: >=3.9
License-File: LICENSE.txt
